<annotation>
	<folder></folder>
	<filename>4_mp4-6_jpg.rf.c25d555d435638fb9bd9e106c52c888d.jpg</filename>
	<path>4_mp4-6_jpg.rf.c25d555d435638fb9bd9e106c52c888d.jpg</path>
	<source>
		<database>roboflow.com</database>
	</source>
	<size>
		<width>640</width>
		<height>640</height>
		<depth>3</depth>
	</size>
	<segmented>0</segmented>
	<object>
		<name>faint</name>
		<pose>Unspecified</pose>
		<truncated>0</truncated>
		<difficult>0</difficult>
		<occluded>0</occluded>
		<bndbox>
			<xmin>33</xmin>
			<xmax>343</xmax>
			<ymin>264</ymin>
			<ymax>356</ymax>
		</bndbox>
	</object>
</annotation>
